uotp/__init__.py
uotp/cli.py
uotp/gui.py
uotp/seed.py
uotp/token.py
uotp/uotp.py
uotp/util.py
uotp/packet/__init__.py
uotp/packet/base.py
uotp/packet/help.py
uotp/packet/information.py
uotp/packet/issue.py
uotp/packet/reset_error_count.py
uotp/packet/time.py
uotp/packet/use_history.py
uotp-0.4.0.dist-info/DESCRIPTION.rst
uotp-0.4.0.dist-info/METADATA
uotp-0.4.0.dist-info/RECORD
uotp-0.4.0.dist-info/WHEEL
uotp-0.4.0.dist-info/entry_points.txt
uotp-0.4.0.dist-info/metadata.json
uotp-0.4.0.dist-info/top_level.txt
