Metadata-Version: 2.0
Name: uotp
Version: 0.4.0
Summary: μOTP+: The next generation OTP toolkit
Home-page: https://github.com/devunt/uotp
Author: Bae Junehyeon
Author-email: devunt@gmail.com
License: Public Domain
Keywords: otp
Platform: UNKNOWN
Classifier: Development Status :: 4 - Beta
Classifier: Environment :: Console
Classifier: Intended Audience :: Developers
Classifier: License :: Public Domain
Classifier: Natural Language :: Korean
Classifier: Natural Language :: English
Classifier: Operating System :: OS Independent
Classifier: Programming Language :: Python
Classifier: Programming Language :: Python :: 3.4
Classifier: Programming Language :: Python :: 3.5
Classifier: Programming Language :: Python :: 3.6
Classifier: Programming Language :: Python :: 3 :: Only
Classifier: Topic :: Security
Classifier: Topic :: Security :: Cryptography
Classifier: Topic :: Utilities
Requires-Python: ~=3.4
Requires-Dist: PyYAML
Requires-Dist: click
Requires-Dist: wxPython
